easy_passgen/__init__.py
easy_passgen/generator.py
easy_passgen-0.1.0.dist-info/METADATA
easy_passgen-0.1.0.dist-info/WHEEL
easy_passgen-0.1.0.dist-info/top_level.txt
easy_passgen-0.1.0.dist-info/RECORD
