Metadata-Version: 2.1
Name: easy_passgen
Version: 0.1.0
Summary: An easy to use password generator
Author: easyPete
